mgkdb/__init__.py
mgkdb/mgk_download.py
mgkdb/mgk_uploader.py
mgkdb/support/ParIO.py
mgkdb/support/__init__.py
mgkdb/support/diag_plot.py
mgkdb/support/fieldlib.py
mgkdb/support/finite_differences.py
mgkdb/support/interp.py
mgkdb/support/mgk_file_handling.py
mgkdb/support/mgk_login.py
mgkdb/support/mgk_post_processing.py
mgkdb/support/mgk_save_credentials.py
mgkdb/support/pyro_gk.py
mgkdb/support/update_metadata.py
mgkdb/support/data/__init__.py
mgkdb/support/data/base_file.py
mgkdb/support/data/data.py
mgkdb/support/data/nrgdata.py
mgkdb/support/data/profiledata.py
mgkdb/support/diagnostics/__init__.py
mgkdb/support/diagnostics/baseplot.py
mgkdb/support/diagnostics/diag_amplitude_spectra.py
mgkdb/support/diagnostics/diag_amplitude_spectra_gene3d.py
mgkdb/support/diagnostics/diag_ballamp.py
mgkdb/support/diagnostics/diag_chivsgradientgene3d.py
mgkdb/support/diagnostics/diag_contours.py
mgkdb/support/diagnostics/diag_correlations.py
mgkdb/support/diagnostics/diag_cross_phase.py
mgkdb/support/diagnostics/diag_derivprofilegene3d.py
mgkdb/support/diagnostics/diag_field_mom_snapshots.py
mgkdb/support/diagnostics/diag_flux_spectra.py
mgkdb/support/diagnostics/diag_fluxesgene3d.py
mgkdb/support/diagnostics/diag_frequencygrate.py
mgkdb/support/diagnostics/diag_planes.py
mgkdb/support/diagnostics/diag_profiles.py
mgkdb/support/diagnostics/diag_shearing_rate.py
mgkdb/support/diagnostics/diag_slicesgene3d.py
mgkdb/support/diagnostics/diag_srcmom.py
mgkdb/support/diagnostics/diag_timetracesgene3d.py
mgkdb/support/diagnostics/diagnostic.py
mgkdb/support/diagnostics/diagspace.py
mgkdb/support/putils/__init__.py
mgkdb/support/putils/aux_func.py
mgkdb/support/putils/averages.py
mgkdb/support/putils/derivatives.py
mgkdb/support/putils/errors.py
mgkdb/support/putils/fourier.py
mgkdb/support/putils/geom.py
mgkdb/support/putils/loader.py
mgkdb/support/putils/par_io.py
mgkdb/support/putils/run.py
mgkdb/support/putils/simulation.py
mgkdb/support/putils/spatial_grid.py
mgkdb-1.0.0.dist-info/METADATA
mgkdb-1.0.0.dist-info/WHEEL
mgkdb-1.0.0.dist-info/entry_points.txt
mgkdb-1.0.0.dist-info/top_level.txt
mgkdb-1.0.0.dist-info/RECORD
