Metadata-Version: 2.4
Name: MGKDB
Version: 1.0.0
Summary: Tools to acess MongoDB for nuclear fusion simulations
Author-email: Craig Michoski <michoski@gmail.com>, Venkitesh Ayyar <venkiteshayyar@gmail.com>, Dongyang Kuang <dykuangii@gmail.com>, David Hatch <drdrhatch@googlemail.com>
License: MIT
Project-URL: Homepage, https://github.com/Sapientai/MGKDB
Classifier: Programming Language :: Python :: 3
Classifier: License :: OSI Approved :: MIT License
Classifier: Operating System :: OS Independent
Requires-Dist: numpy>=1.24.3
Requires-Dist: h5py
Requires-Dist: pymongo
Requires-Dist: pyrokinetics>=0.8.0
